[
  {
    "courseId": "1",
    "className": "English Learning Class",
    "image": "https://ibb.co/jWfHKpP",
    "instructorName": "John Smith",
    "instructorEmail": "john.smith@email.com",
    "price": 49.99,
    "courseStatus": "pending",
    "totalStudent": 15,
    "totalSeat": 20,
    "courseDuration": 6,
    "time": "9:30 am - 10:30 am",
    "daysOfWeek": ["Tuesday", "Thursday", "Saturday"]
  },
  {
    "courseId": "2",
    "className": "German Learning Class",
    "image": "https://ibb.co/T4QTj7J",
    "instructorName": "Anna Müller",
    "instructorEmail": "anna.muller@email.com",
    "price": 59.99,
    "courseStatus": "approved",
    "totalStudent": 10,
    "totalSeat": 15,
    "courseDuration": 8,
    "time": "3:00 pm - 4:00 pm",
    "daysOfWeek": ["Monday", "Wednesday", "FrcourseIday"]
  },
  {
    "courseId": "3",
    "className": "French Learning Class",
    "image": "https://ibb.co/YbGxRGc",
    "instructorName": "Sophie Dubois",
    "instructorEmail": "sophie.dubois@email.com",
    "price": 54.99,
    "courseStatus": "denied",
    "totalStudent": 5,
    "totalSeat": 10,
    "courseDuration": 5,
    "time": "6:00 pm - 7:00 pm",
    "daysOfWeek": ["Wednesday", "FrcourseIday"]
  },
  {
    "courseId": "4",
    "className": "Spanish Learning Class",
    "image": "https://ibb.co/BjXzHJN",
    "instructorName": "Maria Rodriguez",
    "instructorEmail": "maria.rodriguez@email.com",
    "price": 49.99,
    "courseStatus": "approved",
    "totalStudent": 18,
    "totalSeat": 25,
    "courseDuration": 7,
    "time": "10:00 am - 11:00 am",
    "daysOfWeek": ["Monday", "Wednesday", "FrcourseIday"]
  },
  {
    "courseId": "5",
    "className": "Chinese Learning Class",
    "image": "https://ibb.co/D9Pkxf1",
    "instructorName": "Li Wei",
    "instructorEmail": "li.wei@email.com",
    "price": 59.99,
    "courseStatus": "pending",
    "totalStudent": 12,
    "totalSeat": 20,
    "courseDuration": 6,
    "time": "2:30 pm - 3:30 pm",
    "daysOfWeek": ["Tuesday", "Thursday"]
  },
  {
    "courseId": "6",
    "className": "Japanese Learning Class",
    "image": "https://ibb.co/fQs9TnB",
    "instructorName": "Takashi Yamamoto",
    "instructorEmail": "takashi.yamamoto@email.com",
    "price": 54.99,
    "courseStatus": "approved",
    "totalStudent": 8,
    "totalSeat": 15,
    "courseDuration": 8,
    "time": "5:30 pm - 6:30 pm",
    "daysOfWeek": ["Wednesday", "FrcourseIday"]
  },
  {
    "courseId": "7",
    "className": "Italian Learning Class",
    "image": "https://ibb.co/WpGyrbc",
    "instructorName": "Giovanni Russo",
    "instructorEmail": "giovanni.russo@email.com",
    "price": 49.99,
    "courseStatus": "pending",
    "totalStudent": 16,
    "totalSeat": 20,
    "courseDuration": 6,
    "time": "11:00 am - 12:00 pm",
    "daysOfWeek": ["Tuesday", "Thursday", "Saturday"]
  },
  {
    "courseId": "8",
    "className": "Russian Learning Class",
    "image": "https://ibb.co/pLMLVXv",
    "instructorName": "Natalia Ivanova",
    "instructorEmail": "natalia.ivanova@email.com",
    "price": 59.99,
    "courseStatus": "approved",
    "totalStudent": 11,
    "totalSeat": 15,
    "courseDuration": 7,
    "time": "3:30 pm - 4:30 pm",
    "daysOfWeek": ["Monday", "Wednesday", "FrcourseIday"]
  },
  {
    "courseId": "9",
    "className": "Arabic Learning Class",
    "image": "https://ibb.co/ZhfZrt3",
    "instructorName": "Ahmed Hassan",
    "instructorEmail": "ahmed.hassan@email.com",
    "price": 54.99,
    "courseStatus": "denied",
    "totalStudent": 7,
    "totalSeat": 10,
    "courseDuration": 5,
    "time": "7:30 pm - 8:30 pm",
    "daysOfWeek": ["Wednesday", "Saturday"]
  },
  {
    "courseId": "10",
    "className": "Portuguese Learning Class",
    "image": "https://ibb.co/8Nm4CvR",
    "instructorName": "Ana Silva",
    "instructorEmail": "ana.silva@email.com",
    "price": 49.99,
    "courseStatus": "pending",
    "totalStudent": 14,
    "totalSeat": 18,
    "courseDuration": 6,
    "time": "10:30 am - 11:30 am",
    "daysOfWeek": ["Monday", "Wednesday", "FrcourseIday"]
  },
  {
    "courseId": "24",
    "className": "Korean Learning Class",
    "image": "https://ibb.co/D8Ksbw7",
    "instructorName": "Ji-Hoon Kim",
    "instructorEmail": "jihoon.kim@email.com",
    "price": 59.99,
    "courseStatus": "approved",
    "totalStudent": 9,
    "totalSeat": 12,
    "courseDuration": 8,
    "time": "2:00 pm - 3:00 pm",
    "daysOfWeek": ["Tuesday", "Thursday"]
  },
  {
    "courseId": "11",
    "className": "Swedish Learning Class",
    "image": "https://ibb.co/HDmvL1H",
    "instructorName": "Eva Lindström",
    "instructorEmail": "eva.lindstrom@email.com",
    "price": 54.99,
    "courseStatus": "denied",
    "totalStudent": 6,
    "totalSeat": 10,
    "courseDuration": 5,
    "time": "6:30 pm - 7:30 pm",
    "daysOfWeek": ["Thursday", "Saturday"]
  },
  {
    "courseId": "12",
    "className": "Dutch Learning Class",
    "image": "https://ibb.co/RHZH1FQ",
    "instructorName": "Pieter van den Berg",
    "instructorEmail": "pieter.vandenberg@email.com",
    "price": 49.99,
    "courseStatus": "approved",
    "totalStudent": 17,
    "totalSeat": 22,
    "courseDuration": 6,
    "time": "9:00 am - 10:00 am",
    "daysOfWeek": ["Tuesday", "Thursday", "Saturday"]
  },
  {
    "courseId": "13",
    "className": "Turkish Learning Class",
    "image": "https://ibb.co/q06fRFp",
    "instructorName": "Ayse Yilmaz",
    "instructorEmail": "ayse.yilmaz@email.com",
    "price": 59.99,
    "courseStatus": "pending",
    "totalStudent": 13,
    "totalSeat": 20,
    "courseDuration": 7,
    "time": "4:00 pm - 5:00 pm",
    "daysOfWeek": ["Monday", "Wednesday", "FrcourseIday"]
  },
  {
    "courseId": "14",
    "className": "Hindi Learning Class",
    "image": "https://ibb.co/28V3fM1",
    "instructorName": "Raj Kapoor",
    "instructorEmail": "raj.kapoor@email.com",
    "price": 54.99,
    "courseStatus": "denied",
    "totalStudent": 8,
    "totalSeat": 12,
    "courseDuration": 5,
    "time": "5:00 pm - 6:00 pm",
    "daysOfWeek": ["Wednesday", "FrcourseIday"]
  },
  {
    "courseId": "15",
    "className": "Greek Learning Class",
    "image": "https://ibb.co/6t05DgY",
    "instructorName": "Elena Papadopoulos",
    "instructorEmail": "elena.papadopoulos@email.com",
    "price": 49.99,
    "courseStatus": "approved",
    "totalStudent": 18,
    "totalSeat": 18,
    "courseDuration": 6,
    "time": "10:30 am - 11:30 am",
    "daysOfWeek": ["Tuesday", "Thursday", "Saturday"]
  },
  {
    "courseId": "16",
    "className": "Polish Learning Class",
    "image": "https://ibb.co/28YhQXt",
    "instructorName": "Michal Nowak",
    "instructorEmail": "michal.nowak@email.com",
    "price": 59.99,
    "courseStatus": "pending",
    "totalStudent": 11,
    "totalSeat": 15,
    "courseDuration": 7,
    "time": "3:30 pm - 4:30 pm",
    "daysOfWeek": ["Monday", "Wednesday", "FrcourseIday"]
  },
  {
    "courseId": "17",
    "className": "Vietnamese Learning Class",
    "image": "https://ibb.co/nrg3dYd",
    "instructorName": "Linh Nguyen",
    "instructorEmail": "linh.nguyen@email.com",
    "price": 54.99,
    "courseStatus": "denied",
    "totalStudent": 6,
    "totalSeat": 10,
    "courseDuration": 5,
    "time": "7:30 pm - 8:30 pm",
    "daysOfWeek": ["Wednesday", "Saturday"]
  },
  {
    "courseId": "18",
    "className": "Swahili Learning Class",
    "image": "https://ibb.co/MVncPVC",
    "instructorName": "Juma Mbele",
    "instructorEmail": "juma.mbele@email.com",
    "price": 49.99,
    "courseStatus": "pending",
    "totalStudent": 13,
    "totalSeat": 18,
    "courseDuration": 6,
    "time": "11:00 am - 12:00 pm",
    "daysOfWeek": ["Monday", "Wednesday", "FrcourseIday"]
  },
  {
    "courseId": "19",
    "className": "Hebrew Learning Class",
    "image": "https://ibb.co/QjMH2vK",
    "instructorName": "Yael Cohen",
    "instructorEmail": "yael.cohen@email.com",
    "price": 59.99,
    "courseStatus": "approved",
    "totalStudent": 10,
    "totalSeat": 15,
    "courseDuration": 8,
    "time": "2:00 pm - 3:00 pm",
    "daysOfWeek": ["Tuesday", "Thursday"]
  },
  {
    "courseId": "20",
    "className": "Finnish Learning Class",
    "image": "https://ibb.co/cwdS7HC",
    "instructorName": "Mikko Virtanen",
    "instructorEmail": "mikko.virtanen@email.com",
    "price": 54.99,
    "courseStatus": "denied",
    "totalStudent": 7,
    "totalSeat": 10,
    "courseDuration": 5,
    "time": "6:30 pm - 7:30 pm",
    "daysOfWeek": ["Thursday", "Saturday"]
  },
  {
    "courseId": "21",
    "className": "Bengali Learning Class",
    "image": "https://ibb.co/3srqbBs",
    "instructorName": "Ananya Das",
    "instructorEmail": "ananya.das@email.com",
    "price": 49.99,
    "courseStatus": "approved",
    "totalStudent": 16,
    "totalSeat": 20,
    "courseDuration": 6,
    "time": "10:30 am - 11:30 am",
    "daysOfWeek": ["Tuesday", "Thursday", "Saturday"]
  },
  {
    "courseId": "22",
    "className": "Czech Learning Class",
    "image": "https://ibb.co/3srqbBs",
    "instructorName": "Petr Novak",
    "instructorEmail": "petr.novak@email.com",
    "price": 59.99,
    "courseStatus": "pending",
    "totalStudent": 11,
    "totalSeat": 15,
    "courseDuration": 7,
    "time": "3:30 pm - 4:30 pm",
    "daysOfWeek": ["Monday", "Wednesday", "FrcourseIday"]
  },
  {
    "courseId": "23",
    "className": "Tagalog Learning Class",
    "image": "https://ibb.co/6t05DgY",
    "instructorName": "Maria Santos",
    "instructorEmail": "maria.santos@email.com",
    "price": 54.99,
    "courseStatus": "denied",
    "totalStudent": 6,
    "totalSeat": 10,
    "courseDuration": 5,
    "time": "7:30 pm - 8:30 pm",
    "daysOfWeek": ["Wednesday", "Saturday"]
  }
]
